{"group": [{"pic_list": ["20597782010200004688", "20597782010200004689", "20597782010200004690"], "seq_id": "A"}, {"pic_list": ["18558607083100047188", "18558607083100047189", "18558607083100047190", "18558607083100047191", "18558607083100052241"], "seq_id": "B"}], "signs": [{"pic_id": "20597782010200004688", "x": 145, "y": 336, "w": 29, "h": 26, "type": "201", "sign_id": "sign_A_1"}, {"pic_id": "20597782010200004688", "x": 182, "y": 266, "w": 9, "h": 11, "type": "301", "sign_id": "sign_A_2"}, {"pic_id": "20597782010200004688", "x": 93, "y": 282, "w": 11, "h": 12, "type": "301", "sign_id": "sign_A_3"}, {"pic_id": "20597782010200004689", "x": 2, "y": 216, "w": 11, "h": 13, "type": "301", "sign_id": "sign_A_4"}, {"pic_id": "18558607083100047188", "x": 309, "y": 401, "w": 34, "h": 34, "type": "201", "sign_id": "sign_B_1"}, {"pic_id": "18558607083100047188", "x": 239, "y": 333, "w": 13, "h": 16, "type": "301", "sign_id": "sign_B_2"}, {"pic_id": "18558607083100047188", "x": 345, "y": 312, "w": 10, "h": 13, "type": "301", "sign_id": "sign_B_3"}, {"pic_id": "18558607083100047189", "x": 115, "y": 350, "w": 57, "h": 46, "type": "201", "sign_id": "sign_B_4"}, {"pic_id": "18558607083100047189", "x": 200, "y": 216, "w": 16, "h": 19, "type": "301", "sign_id": "sign_B_5"}, {"pic_id": "18558607083100047189", "x": 0, "y": 236, "w": 16, "h": 24, "type": "301", "sign_id": "sign_B_6"}, {"pic_id": "18558607083100047190", "x": 490, "y": 421, "w": 25, "h": 22, "type": "201", "sign_id": "sign_B_7"}, {"pic_id": "18558607083100047190", "x": 61, "y": 149, "w": 20, "h": 25, "type": "301", "sign_id": "sign_B_8"}, {"pic_id": "18558607083100047191", "x": 445, "y": 414, "w": 30, "h": 28, "type": "201", "sign_id": "sign_B_9"}, {"pic_id": "18558607083100052241", "x": 433, "y": 409, "w": 32, "h": 30, "type": "201", "sign_id": "sign_B_10"}], "match": [{"sign_id": "sign_A_1", "match_sign_id": "sign_B_4"}, {"sign_id": "sign_A_1", "match_sign_id": "sign_B_1"}, {"sign_id": "sign_A_1", "match_sign_id": "sign_B_7"}, {"sign_id": "sign_A_1", "match_sign_id": "sign_B_9"}, {"sign_id": "sign_A_1", "match_sign_id": "sign_B_10"}, {"sign_id": "sign_B_5", "match_sign_id": "sign_A_2"}, {"sign_id": "sign_A_2", "match_sign_id": "sign_B_3"}, {"sign_id": "sign_A_2", "match_sign_id": "sign_B_6"}, {"sign_id": "sign_A_2", "match_sign_id": "sign_B_8"}, {"sign_id": "sign_A_2", "match_sign_id": "sign_B_2"}, {"sign_id": "sign_A_2", "match_sign_id": "sign_B_1"}, {"sign_id": "sign_A_2", "match_sign_id": "sign_B_4"}, {"sign_id": "sign_B_6", "match_sign_id": "sign_A_3"}, {"sign_id": "sign_A_3", "match_sign_id": "sign_B_8"}, {"sign_id": "sign_B_5", "match_sign_id": "sign_A_3"}, {"sign_id": "sign_A_3", "match_sign_id": "sign_B_3"}, {"sign_id": "sign_A_3", "match_sign_id": "sign_B_1"}, {"sign_id": "sign_A_3", "match_sign_id": "sign_B_2"}, {"sign_id": "sign_A_3", "match_sign_id": "sign_B_4"}, {"sign_id": "sign_B_6", "match_sign_id": "sign_A_4"}, {"sign_id": "sign_B_5", "match_sign_id": "sign_A_4"}, {"sign_id": "sign_B_8", "match_sign_id": "sign_A_4"}, {"sign_id": "sign_A_4", "match_sign_id": "sign_B_3"}, {"sign_id": "sign_A_4", "match_sign_id": "sign_B_2"}, {"sign_id": "sign_A_4", "match_sign_id": "sign_B_1"}, {"sign_id": "sign_A_4", "match_sign_id": "sign_B_4"}]}